dbaas_base_provider/version.py
dbaas_base_provider/log.py
dbaas_base_provider/baseCredential.py
dbaas_base_provider/__init__.py
dbaas_base_provider/team.py
dbaas_base_provider/baseProvider.py
dbaas_base_provider/base.py
dbaas_base_provider-0.0.27.dist-info/pydist.json
dbaas_base_provider-0.0.27.dist-info/RECORD
dbaas_base_provider-0.0.27.dist-info/WHEEL
dbaas_base_provider-0.0.27.dist-info/DESCRIPTION.rst
dbaas_base_provider-0.0.27.dist-info/top_level.txt
dbaas_base_provider-0.0.27.dist-info/METADATA
