Metadata-Version: 2.0
Name: dbaas-base-provider
Version: 0.0.27
Summary: Base for DBaaS providers
Home-page: https://github.com/bento-dbaas/dbaas-base-provider
Author: William Marquardt
Author-email: williammqt@gmail.com
License: BSD 3-Clause License
Keywords: dbaas
Platform: UNKNOWN
Classifier: Development Status :: 5 - Production/Stable
Requires-Dist: mongoengine (>=0.15.0)
Requires-Dist: pymongo (==3.6.1)
Requires-Dist: python-slugify (==4.0.1)
